dice.py
dice_sim-1.0.0.dist-info/DESCRIPTION.rst
dice_sim-1.0.0.dist-info/METADATA
dice_sim-1.0.0.dist-info/RECORD
dice_sim-1.0.0.dist-info/WHEEL
dice_sim-1.0.0.dist-info/entry_points.txt
dice_sim-1.0.0.dist-info/metadata.json
dice_sim-1.0.0.dist-info/top_level.txt
