Metadata-Version: 2.0
Name: dice-sim
Version: 1.0.0
Summary: Simulate various dice throw situations
Home-page: https://github.com/samuller/dice
Author: Simon Muller
Author-email: samullers@gmail.com
License: UNKNOWN
Platform: UNKNOWN
Classifier: Development Status :: 5 - Production/Stable
Classifier: Environment :: Console
Classifier: Intended Audience :: Other Audience
Classifier: License :: OSI Approved :: GNU Lesser General Public License v2 (LGPLv2)
Classifier: Natural Language :: English
Classifier: Programming Language :: Python
Classifier: Topic :: Games/Entertainment
Classifier: Topic :: Games/Entertainment :: Board Games
Classifier: Topic :: Utilities
